cev_metrics-0.1.5.dist-info/METADATA
cev_metrics-0.1.5.dist-info/WHEEL
cev_metrics/__init__.py
cev_metrics/_rust.py
cev_metrics/cev_metrics.pypy39-pp73-arm-linux-gnu.so
cev_metrics-0.1.5.dist-info/RECORD
