Metadata-Version: 2.3
Name: cev-metrics
Version: 0.1.5
Requires-Dist: numpy
Summary: Rust implementations of our embedding comparison metrics, exposed via Python bindings.
Author-email: Trevor Manz <trevor.j.manz@gmail.com>
Requires-Python: >=3.9
